{"data_mtime": 1687981669, "dep_lines": [50, 54, 56, 56, 57, 57, 58, 59, 60, 62, 65, 65, 70, 70, 71, 71, 14, 51, 61, 63, 64, 66, 67, 68, 69, 1, 1, 1, 1, 1, 1, 1, 1, 1, 1, 1, 1, 1, 1, 1, 1, 1, 1, 1, 1, 1, 1, 1, 1, 1, 1], "dep_prios": [10, 10, 10, 20, 10, 20, 10, 10, 10, 10, 10, 20, 10, 20, 5, 20, 5, 5, 5, 5, 5, 5, 5, 5, 5, 5, 30, 30, 30, 30, 30, 30, 30, 30, 30, 30, 30, 30, 30, 30, 30, 30, 30, 30, 30, 30, 30, 30, 30, 30, 30], "dependencies": ["functools", "numpy", "jax.lax", "jax", "jax._src.core", "jax._src", "jax._src.linear_util", "jax._src.pjit", "jax._src.sharding_impls", "jax.numpy", "jax._src.interpreters.partial_eval", "jax._src.interpreters", "jax._src.numpy.lax_numpy", "jax._src.numpy", "jax.experimental.sparse", "jax.experimental", "__future__", "typing", "jax.experimental.sparse.bcoo", "jax._src.api_util", "jax._src.lib", "jax.tree_util", "jax.util", "jax._src.config", "jax._src.lax.control_flow", "builtins", "_collections_abc", "_typeshed", "abc", "contextlib", "enum", "jax._src.basearray", "jax._src.lax", "jax._src.lax.control_flow.common", "jax._src.lax.lax", "jax._src.lax.slicing", "jax._src.numpy.ufuncs", "jax._src.stages", "jax._src.tree_util", "jax._src.typing", "jax._src.util", "jax.experimental.sparse._base", "jax.experimental.sparse.bcsr", "jaxlib", "jaxlib.xla_extension", "jaxlib.xla_extension.pytree", "numpy._typing", "numpy._typing._array_like", "numpy._typing._nested_sequence", "types", "typing_extensions"], "hash": "6d500f10b7748f15b27acf905a4bfb557717c0ad92689ae4df3a2c9ec9314e19", "id": "jax.experimental.sparse.transform", "ignore_all": true, "interface_hash": "768ffcbc31591e82ab56f3941ebc6ea4822686b08af5d8eaff3a199723153380", "mtime": 1687981167, "options": {"allow_redefinition": false, "allow_untyped_globals": false, "always_false": [], "always_true": [], "bazel": false, "check_untyped_defs": false, "disallow_any_decorated": false, "disallow_any_explicit": false, "disallow_any_expr": false, "disallow_any_generics": false, "disallow_any_unimported": false, "disallow_incomplete_defs": false, "disallow_subclassing_any": false, "disallow_untyped_calls": false, "disallow_untyped_decorators": false, "disallow_untyped_defs": false, "follow_imports": "silent", "follow_imports_for_stubs": false, "ignore_errors": false, "ignore_missing_imports": true, "implicit_reexport": true, "local_partial_types": false, "mypyc": false, "no_implicit_optional": false, "platform": "darwin", "plugins": [], "show_none_errors": true, "strict_concatenate": false, "strict_equality": false, "strict_optional": true, "strict_optional_whitelist": null, "warn_no_return": true, "warn_return_any": false, "warn_unreachable": false, "warn_unused_ignores": false}, "path": "/opt/homebrew/Caskroom/miniconda/base/envs/main/lib/python3.10/site-packages/jax/experimental/sparse/transform.py", "plugin_data": null, "size": 35752, "suppressed": [], "version_id": "0.971"}